MANIFEST.in
README.md
requirements.txt
setup.py
aws_ec2_scheduler.egg-info/PKG-INFO
aws_ec2_scheduler.egg-info/SOURCES.txt
aws_ec2_scheduler.egg-info/dependency_links.txt
aws_ec2_scheduler.egg-info/entry_points.txt
aws_ec2_scheduler.egg-info/not-zip-safe
aws_ec2_scheduler.egg-info/requires.txt
aws_ec2_scheduler.egg-info/top_level.txt
ec2scheduler/__init__.py
ec2scheduler/aws.conf.dist
ec2scheduler/schedule.json.dist
ec2scheduler/scheduler.py