Metadata-Version: 1.0
Name: aws-ec2-scheduler
Version: 1.0
Summary: A scheduling script for aws ec2 instances
Home-page: https://github.com/mlimaloureiro/ec2scheduler
Author: mlimaloureiro
Author-email: mdiasloureiro@gmail.com
License: MIT
Platform: UNKNOWN
